llmkit/__init__.py
llmkit/__init__.pyi
llmkit/_llmkit.abi3.so
llmkit/py.typed
llmkit_python-0.1.3.dist-info/METADATA
llmkit_python-0.1.3.dist-info/WHEEL
llmkit_python-0.1.3.dist-info/RECORD
