Metadata-Version: 2.4
Name: llmkit-python
Version: 0.1.3
Classifier: Development Status :: 4 - Beta
Classifier: Intended Audience :: Developers
Classifier: License :: OSI Approved :: MIT License
Classifier: License :: OSI Approved :: Apache Software License
Classifier: Programming Language :: Python :: 3
Classifier: Programming Language :: Python :: 3.8
Classifier: Programming Language :: Python :: 3.9
Classifier: Programming Language :: Python :: 3.10
Classifier: Programming Language :: Python :: 3.11
Classifier: Programming Language :: Python :: 3.12
Classifier: Programming Language :: Python :: Implementation :: CPython
Classifier: Programming Language :: Rust
Classifier: Topic :: Scientific/Engineering :: Artificial Intelligence
Classifier: Typing :: Typed
Summary: Production-grade LLM client for Python - 100+ providers, 11,000+ models. Rust-powered.
Keywords: llm,ai,openai,anthropic,claude,gpt,llama
License: MIT OR Apache-2.0
Requires-Python: >=3.8
Project-URL: Documentation, https://github.com/yfedoseev/llmkit#readme
Project-URL: Homepage, https://github.com/yfedoseev/llmkit
Project-URL: Repository, https://github.com/yfedoseev/llmkit
